{
  "scenario": "double_bridge",
  "literature_target": "Deneubourg-style equal-branch symmetry breaking",
  "parameters": {
    "seeds": "1-8",
    "days": 8.0,
    "sample_days": 0.1,
    "dt": 9.0,
    "ants": 240,
    "species": "lasius",
    "food_amount": 1800,
    "pheromone_strength": 120.0,
    "diffusion_rate": 100.0,
    "evaporation_rate": 80.0,
    "sense_threshold": 10.0,
    "bias_branch": "none",
    "bias_strength": 0,
    "output": "/home/s92137/ant_colony_sim/calibration_results/double_bridge_runs/005_pheromoneStrength-120_senseThreshold-10_evaporationRate-80_equal.csv",
    "metadata": null
  },
  "summary": {
    "runs": 8,
    "upper_selected": 2,
    "lower_selected": 6,
    "ties": 0,
    "mean_dominance": 0.1992,
    "mean_food_trips": 267.5
  },
  "rows": [
    {
      "seed": 1,
      "species": "lasius",
      "ants": 241,
      "days": 8,
      "bias_branch": "none",
      "bias_strength": 0,
      "upper_crossings": 860,
      "lower_crossings": 895,
      "total_crossings": 1755,
      "upper_return_crossings": 258,
      "lower_return_crossings": 273,
      "return_crossings": 531,
      "selected_branch": "lower",
      "return_selected_branch": "lower",
      "dominance": 0.0199,
      "return_dominance": 0.0282,
      "food_trips": 132,
      "food_collected": 651,
      "food_pheromone": 38727,
      "upper_food_pheromone": 1294,
      "lower_food_pheromone": 1675,
      "final_ants": 241,
      "dead": 0
    },
    {
      "seed": 2,
      "species": "lasius",
      "ants": 240,
      "days": 8,
      "bias_branch": "none",
      "bias_strength": 0,
      "upper_crossings": 465,
      "lower_crossings": 1065,
      "total_crossings": 1530,
      "upper_return_crossings": 108,
      "lower_return_crossings": 312,
      "return_crossings": 420,
      "selected_branch": "lower",
      "return_selected_branch": "lower",
      "dominance": 0.3922,
      "return_dominance": 0.4857,
      "food_trips": 356,
      "food_collected": 1776,
      "food_pheromone": 4583,
      "upper_food_pheromone": 47,
      "lower_food_pheromone": 163,
      "final_ants": 240,
      "dead": 0
    },
    {
      "seed": 3,
      "species": "lasius",
      "ants": 241,
      "days": 8,
      "bias_branch": "none",
      "bias_strength": 0,
      "upper_crossings": 890,
      "lower_crossings": 1040,
      "total_crossings": 1930,
      "upper_return_crossings": 152,
      "lower_return_crossings": 204,
      "return_crossings": 356,
      "selected_branch": "lower",
      "return_selected_branch": "lower",
      "dominance": 0.0777,
      "return_dominance": 0.1461,
      "food_trips": 246,
      "food_collected": 1197,
      "food_pheromone": 41694,
      "upper_food_pheromone": 1480,
      "lower_food_pheromone": 1470,
      "final_ants": 241,
      "dead": 0
    },
    {
      "seed": 4,
      "species": "lasius",
      "ants": 240,
      "days": 8,
      "bias_branch": "none",
      "bias_strength": 0,
      "upper_crossings": 769,
      "lower_crossings": 1136,
      "total_crossings": 1905,
      "upper_return_crossings": 136,
      "lower_return_crossings": 298,
      "return_crossings": 434,
      "selected_branch": "lower",
      "return_selected_branch": "lower",
      "dominance": 0.1927,
      "return_dominance": 0.3733,
      "food_trips": 287,
      "food_collected": 1453,
      "food_pheromone": 42689,
      "upper_food_pheromone": 643,
      "lower_food_pheromone": 1959,
      "final_ants": 240,
      "dead": 0
    },
    {
      "seed": 5,
      "species": "lasius",
      "ants": 240,
      "days": 8,
      "bias_branch": "none",
      "bias_strength": 0,
      "upper_crossings": 1057,
      "lower_crossings": 840,
      "total_crossings": 1897,
      "upper_return_crossings": 276,
      "lower_return_crossings": 193,
      "return_crossings": 469,
      "selected_branch": "upper",
      "return_selected_branch": "upper",
      "dominance": 0.1144,
      "return_dominance": 0.177,
      "food_trips": 240,
      "food_collected": 1173,
      "food_pheromone": 43514,
      "upper_food_pheromone": 1998,
      "lower_food_pheromone": 1201,
      "final_ants": 240,
      "dead": 0
    },
    {
      "seed": 6,
      "species": "lasius",
      "ants": 240,
      "days": 8,
      "bias_branch": "none",
      "bias_strength": 0,
      "upper_crossings": 1186,
      "lower_crossings": 610,
      "total_crossings": 1796,
      "upper_return_crossings": 373,
      "lower_return_crossings": 110,
      "return_crossings": 483,
      "selected_branch": "upper",
      "return_selected_branch": "upper",
      "dominance": 0.3207,
      "return_dominance": 0.5445,
      "food_trips": 355,
      "food_collected": 1784,
      "food_pheromone": 5703,
      "upper_food_pheromone": 178,
      "lower_food_pheromone": 144,
      "final_ants": 240,
      "dead": 0
    },
    {
      "seed": 7,
      "species": "lasius",
      "ants": 241,
      "days": 8,
      "bias_branch": "none",
      "bias_strength": 0,
      "upper_crossings": 629,
      "lower_crossings": 1009,
      "total_crossings": 1638,
      "upper_return_crossings": 85,
      "lower_return_crossings": 205,
      "return_crossings": 290,
      "selected_branch": "lower",
      "return_selected_branch": "lower",
      "dominance": 0.232,
      "return_dominance": 0.4138,
      "food_trips": 167,
      "food_collected": 819,
      "food_pheromone": 38729,
      "upper_food_pheromone": 480,
      "lower_food_pheromone": 1770,
      "final_ants": 241,
      "dead": 0
    },
    {
      "seed": 8,
      "species": "lasius",
      "ants": 240,
      "days": 8,
      "bias_branch": "none",
      "bias_strength": 0,
      "upper_crossings": 727,
      "lower_crossings": 1197,
      "total_crossings": 1924,
      "upper_return_crossings": 149,
      "lower_return_crossings": 349,
      "return_crossings": 498,
      "selected_branch": "lower",
      "return_selected_branch": "lower",
      "dominance": 0.2443,
      "return_dominance": 0.4016,
      "food_trips": 357,
      "food_collected": 1780,
      "food_pheromone": 5533,
      "upper_food_pheromone": 124,
      "lower_food_pheromone": 174,
      "final_ants": 240,
      "dead": 0
    }
  ]
}